jsobject2/__init__.py
jsobject2/_jsobject2.py
jsobject2-0.0.2.dist-info/LICENSE
jsobject2-0.0.2.dist-info/METADATA
jsobject2-0.0.2.dist-info/WHEEL
jsobject2-0.0.2.dist-info/top_level.txt
jsobject2-0.0.2.dist-info/RECORD
