Metadata-Version: 2.1
Name: jsobject2
Version: 0.0.2
Summary: Make Python dict support the access method of JavaScript Object.
Home-page: https://github.com/nanako-seven/jsobject2
Author: nanako
Author-email: anguuan@outlook.com
License: UNKNOWN
Project-URL: Bug Tracker, https://github.com/nanako-seven/jsobject2/issues
Platform: UNKNOWN
Classifier: Programming Language :: Python :: 3
Classifier: License :: OSI Approved :: BSD License
Classifier: Operating System :: OS Independent
Requires-Python: >=3.6
License-File: LICENSE
